gxy_bailian_mcp_server/__init__.py
gxy_bailian_mcp_server/app.py
gxy_bailian_mcp_server-0.3.0.dist-info/WHEEL
gxy_bailian_mcp_server-0.3.0.dist-info/entry_points.txt
gxy_bailian_mcp_server-0.3.0.dist-info/METADATA
gxy_bailian_mcp_server-0.3.0.dist-info/RECORD
